youtube_downloader_pkg/__init__.py
youtube_downloader_pkg/__main__.py
youtube_downloader_pkg/downloader.py
yt_dl_easy-0.1.1.dist-info/LICENSE
yt_dl_easy-0.1.1.dist-info/METADATA
yt_dl_easy-0.1.1.dist-info/WHEEL
yt_dl_easy-0.1.1.dist-info/entry_points.txt
yt_dl_easy-0.1.1.dist-info/top_level.txt
yt_dl_easy-0.1.1.dist-info/RECORD
